{"created_at": "Fri Mar 15 02:51:25 +0000 2019", "id": 1106387393790173184, "id_str": "1106387393790173184", "text": "@TwitterMoments @hallmarkchannel Looks like #AuntBecky and her spoiled brats will be made an example of as they sho\u2026 https://t.co/npaxy5DNVh", "truncated": true, "entities": {"hashtags": [{"text": "AuntBecky", "indices": [44, 54]}], "symbols": [], "user_mentions": [{"screen_name": "TwitterMoments", "name": "Twitter Moments", "id": 3260518932, "id_str": "3260518932", "indices": [0, 15]}, {"screen_name": "hallmarkchannel", "name": "Hallmark Channel", "id": 25453312, "id_str": "25453312", "indices": [16, 32]}], "urls": [{"url": "https://t.co/npaxy5DNVh", "expanded_url": "https://twitter.com/i/web/status/1106387393790173184", "display_url": "twitter.com/i/web/status/1\u2026", "indices": [117, 140]}]}, "source": "<a href=\"http://twitter.com/download/iphone\" rel=\"nofollow\">Twitter for iPhone</a>", "in_reply_to_status_id": 1106295862324531203, "in_reply_to_status_id_str": "1106295862324531203", "in_reply_to_user_id": 3260518932, "in_reply_to_user_id_str": "3260518932", "in_reply_to_screen_name": "TwitterMoments", "user": {"id": 2961939470, "id_str": "2961939470", "name": "Dan Vossler", "screen_name": "Danothemechano", "location": "Calgary Alberta", "description": "Not in this to win it.Liker of hockey and other stuff.Sun and fun seeker.Critic of all things critical.", "url": "https://t.co/kkYhegL6Jo", "entities": {"url": {"urls": [{"url": "https://t.co/kkYhegL6Jo", "expanded_url": "http://www.upyours.com", "display_url": "upyours.com", "indices": [0, 23]}]}, "description": {"urls": []}}, "protected": false, "followers_count": 26, "friends_count": 99, "listed_count": 0, "created_at": "Wed Jan 07 03:14:16 +0000 2015", "favourites_count": 2783, "utc_offset": null, "time_zone": null, "geo_enabled": true, "verified": false, "statuses_count": 531, "lang": "en", "contributors_enabled": false, "is_translator": false, "is_translation_enabled": false, "profile_background_color": "C0DEED", "profile_background_image_url": "http://abs.twimg.com/images/themes/theme1/bg.png", "profile_background_image_url_https": "https://abs.twimg.com/images/themes/theme1/bg.png", "profile_background_tile": false, "profile_image_url": "http://pbs.twimg.com/profile_images/916865674021978112/iFXIPFxk_normal.jpg", "profile_image_url_https": "https://pbs.twimg.com/profile_images/916865674021978112/iFXIPFxk_normal.jpg", "profile_banner_url": "https://pbs.twimg.com/profile_banners/2961939470/1475046219", "profile_link_color": "1DA1F2", "profile_sidebar_border_color": "C0DEED", "profile_sidebar_fill_color": "DDEEF6", "profile_text_color": "333333", "profile_use_background_image": true, "has_extended_profile": true, "default_profile": true, "default_profile_image": false, "following": false, "follow_request_sent": false, "notifications": false, "translator_type": "none"}, "geo": null, "coordinates": null, "place": null, "contributors": null, "is_quote_status": false, "retweet_count": 0, "favorite_count": 2, "favorited": false, "retweeted": false, "possibly_sensitive": false, "possibly_sensitive_appealable": false, "lang": "en"}
