{"created_at": "Thu Mar 14 21:04:26 +0000 2019", "id": 1106300074500460548, "id_str": "1106300074500460548", "text": "Sounds about white  #OperationVarsityBlues https://t.co/uW2sYrCa59", "truncated": false, "entities": {"hashtags": [{"text": "OperationVarsityBlues", "indices": [20, 42]}], "symbols": [], "user_mentions": [], "urls": [], "media": [{"id": 1106300063997968384, "id_str": "1106300063997968384", "indices": [43, 66], "media_url": "http://pbs.twimg.com/tweet_video_thumb/D1peC_mXQAAa6vd.jpg", "media_url_https": "https://pbs.twimg.com/tweet_video_thumb/D1peC_mXQAAa6vd.jpg", "url": "https://t.co/uW2sYrCa59", "display_url": "pic.twitter.com/uW2sYrCa59", "expanded_url": "https://twitter.com/dxtrldn/status/1106300074500460548/photo/1", "type": "photo", "sizes": {"large": {"w": 272, "h": 136, "resize": "fit"}, "small": {"w": 272, "h": 136, "resize": "fit"}, "medium": {"w": 272, "h": 136, "resize": "fit"}, "thumb": {"w": 136, "h": 136, "resize": "crop"}}}]}, "extended_entities": {"media": [{"id": 1106300063997968384, "id_str": "1106300063997968384", "indices": [43, 66], "media_url": "http://pbs.twimg.com/tweet_video_thumb/D1peC_mXQAAa6vd.jpg", "media_url_https": "https://pbs.twimg.com/tweet_video_thumb/D1peC_mXQAAa6vd.jpg", "url": "https://t.co/uW2sYrCa59", "display_url": "pic.twitter.com/uW2sYrCa59", "expanded_url": "https://twitter.com/dxtrldn/status/1106300074500460548/photo/1", "type": "animated_gif", "sizes": {"large": {"w": 272, "h": 136, "resize": "fit"}, "small": {"w": 272, "h": 136, "resize": "fit"}, "medium": {"w": 272, "h": 136, "resize": "fit"}, "thumb": {"w": 136, "h": 136, "resize": "crop"}}, "video_info": {"aspect_ratio": [2, 1], "variants": [{"bitrate": 0, "content_type": "video/mp4", "url": "https://video.twimg.com/tweet_video/D1peC_mXQAAa6vd.mp4"}]}}]}, "source": "<a href=\"http://twitter.com/download/iphone\" rel=\"nofollow\">Twitter for iPhone</a>", "in_reply_to_status_id": null, "in_reply_to_status_id_str": null, "in_reply_to_user_id": null, "in_reply_to_user_id_str": null, "in_reply_to_screen_name": null, "user": {"id": 997900711684866048, "id_str": "997900711684866048", "name": "\ud83e\udd87\ud83c\udf0d\u267b\ufe0f\ud83d\udc9a\ud83c\udff4\u200d\u2620\ufe0f", "screen_name": "dxtrldn", "location": "United Kingdom", "description": "oh hey. #BTPosse", "url": null, "entities": {"description": {"urls": []}}, "protected": false, "followers_count": 29, "friends_count": 150, "listed_count": 0, "created_at": "Sat May 19 18:04:04 +0000 2018", "favourites_count": 1611, "utc_offset": null, "time_zone": null, "geo_enabled": false, "verified": false, "statuses_count": 1412, "lang": "en", "contributors_enabled": false, "is_translator": false, "is_translation_enabled": false, "profile_background_color": "F5F8FA", "profile_background_image_url": null, "profile_background_image_url_https": null, "profile_background_tile": false, "profile_image_url": "http://pbs.twimg.com/profile_images/1114087768555237376/cNDOxoLb_normal.jpg", "profile_image_url_https": "https://pbs.twimg.com/profile_images/1114087768555237376/cNDOxoLb_normal.jpg", "profile_banner_url": "https://pbs.twimg.com/profile_banners/997900711684866048/1531542058", "profile_link_color": "1DA1F2", "profile_sidebar_border_color": "C0DEED", "profile_sidebar_fill_color": "DDEEF6", "profile_text_color": "333333", "profile_use_background_image": true, "has_extended_profile": false, "default_profile": true, "default_profile_image": false, "following": false, "follow_request_sent": false, "notifications": false, "translator_type": "none"}, "geo": null, "coordinates": null, "place": null, "contributors": null, "is_quote_status": false, "retweet_count": 0, "favorite_count": 1, "favorited": false, "retweeted": false, "possibly_sensitive": false, "possibly_sensitive_appealable": false, "lang": "en"}
